py.typed
circlemind_sdk/__init__.py
circlemind_sdk/_hooks/__init__.py
circlemind_sdk/_hooks/registration.py
circlemind_sdk/_hooks/sdkhooks.py
circlemind_sdk/_hooks/types.py
circlemind_sdk/_version.py
circlemind_sdk/basesdk.py
circlemind_sdk/httpclient.py
circlemind_sdk/models/__init__.py
circlemind_sdk/models/body_post_insert_files_graph_graph_name_files_post.py
circlemind_sdk/models/configurerequest.py
circlemind_sdk/models/configureresponse.py
circlemind_sdk/models/create_graph_graph_graph_name_postop.py
circlemind_sdk/models/delete_graph_graph_graph_name_delete_postop.py
circlemind_sdk/models/downloadgraphresponse.py
circlemind_sdk/models/get_graph_configuration_graph_graph_name_configuration_getop.py
circlemind_sdk/models/get_graphml_graph_graph_name_graphml_getop.py
circlemind_sdk/models/get_insert_status_graph_graph_name_insert_request_id_getop.py
circlemind_sdk/models/get_query_status_graph_graph_name_query_request_id_getop.py
circlemind_sdk/models/graphlistresponse.py
circlemind_sdk/models/httpvalidationerror.py
circlemind_sdk/models/insertrequest.py
circlemind_sdk/models/insertresponse.py
circlemind_sdk/models/planresponse.py
circlemind_sdk/models/post_graph_configuration_graph_graph_name_configuration_postop.py
circlemind_sdk/models/post_insert_files_graph_graph_name_files_postop.py
circlemind_sdk/models/post_insert_graph_graph_name_insert_postop.py
circlemind_sdk/models/post_query_graph_graph_name_query_postop.py
circlemind_sdk/models/queryrequest.py
circlemind_sdk/models/queryresponse.py
circlemind_sdk/models/requeststatus.py
circlemind_sdk/models/sdkerror.py
circlemind_sdk/models/security.py
circlemind_sdk/models/validationerror.py
circlemind_sdk/py.typed
circlemind_sdk/sdk.py
circlemind_sdk/sdkconfiguration.py
circlemind_sdk/types/__init__.py
circlemind_sdk/types/basemodel.py
circlemind_sdk/utils/__init__.py
circlemind_sdk/utils/annotations.py
circlemind_sdk/utils/enums.py
circlemind_sdk/utils/eventstreaming.py
circlemind_sdk/utils/forms.py
circlemind_sdk-0.1.0.post0.dist-info/METADATA
circlemind_sdk-0.1.0.post0.dist-info/WHEEL
circlemind_sdk-0.1.0.post0.dist-info/RECORD
